{
  "name": "m7i",
  "regions": [
    "ap-southeast-2",
    "ap-south-1",
    "ap-northeast-2",
    "eu-west-1",
    "us-west-1",
    "us-west-2",
    "ca-central-1",
    "eu-central-1",
    "eu-west-3",
    "us-east-1",
    "us-east-2",
    "eu-south-2",
    "eu-north-1",
    "eu-west-2"
  ],
  "sizes": [
    "16xlarge",
    "metal-24xl",
    "2xlarge",
    "24xlarge",
    "8xlarge",
    "48xlarge",
    "large",
    "xlarge",
    "4xlarge",
    "12xlarge",
    "metal-48xl"
  ],
  "currentGeneration": true,
  "cpu": {
    "architectures": [
      "x86_64"
    ],
    "minThreads": 2,
    "maxCores": 192
  },
  "memory": {
    "minMib": 8192,
    "maxMib": 786432
  }
}